sfps/__init__.py
sfps/sfps.py
sfps-0.0.0.dist-info/LICENSE
sfps-0.0.0.dist-info/METADATA
sfps-0.0.0.dist-info/WHEEL
sfps-0.0.0.dist-info/top_level.txt
sfps-0.0.0.dist-info/RECORD
