Metadata-Version: 2.1
Name: sfps
Version: 0.0.0
Summary: SFPS - Smooth FPS.
Home-page: https://github.com/rathaROG/smooth-fps
Author: Ratha SIV
Maintainer: rathaROG
License: BSD-2-Clause
Keywords: SFPS,FPS,Frame rate,FPS calculator
Classifier: Development Status :: 4 - Beta
Classifier: Environment :: Console
Classifier: Intended Audience :: Developers
Classifier: Intended Audience :: Education
Classifier: Intended Audience :: Science/Research
Classifier: License :: OSI Approved :: BSD License
Classifier: Programming Language :: Python :: 3
Classifier: Topic :: Education
Classifier: Topic :: Education :: Testing
Classifier: Topic :: Scientific/Engineering
Classifier: Topic :: Scientific/Engineering :: Mathematics
Classifier: Topic :: Software Development
Classifier: Topic :: Software Development :: Libraries
Classifier: Operating System :: Microsoft :: Windows
Classifier: Operating System :: POSIX
Classifier: Operating System :: Unix
Classifier: Operating System :: MacOS
License-File: LICENSE
